pyspa/__init__.py
pyspa/pyspa.py
template_input_files/A_matrix_template.csv
template_input_files/Infosheet_template.csv
template_input_files/Thresholds_template.csv
template_input_files/Thresholds_template_perc.csv
template_input_files/__init__.py
pyspa-2.4.dist-info/LICENSE.txt
pyspa-2.4.dist-info/METADATA
pyspa-2.4.dist-info/WHEEL
pyspa-2.4.dist-info/top_level.txt
pyspa-2.4.dist-info/RECORD
