Metadata-Version: 2.1
Name: pyspa
Version: 2.4
Summary: An object-oriented python package for advanced structural path analysis
Home-page: https://github.com/hybridlca/pyspa
Author: André Stephan & Paul-Antoine Bontinck
Author-email: stephan.andre@gmail.com
License: GNU General Public License v3.0
License-File: LICENSE.txt
Requires-Dist: numpy
Requires-Dist: pandas
Requires-Dist: scipy
